tfrecords/README.md
tfrecords/__init__.py
tfrecords/version_config.py
tfrecords/lib/__init__.py
tfrecords/lib/arrow_cc.pyd
tfrecords/lib/arrow_lib.py
tfrecords/lib/fix.py
tfrecords/lib/tfrecords_cc.pyd
tfrecords/lib/tfrecords_lib.py
tfrecords/python/__init__.py
tfrecords/python/framework/__init__.py
tfrecords/python/framework/errors.py
tfrecords/python/io/__init__.py
tfrecords/python/io/arrow.py
tfrecords/python/io/file_io.py
tfrecords/python/io/file_io_test.py
tfrecords/python/io/gfile.py
tfrecords/python/io/tf_leveldb.py
tfrecords/python/io/tf_lmdb.py
tfrecords/python/io/tf_record.py
tfrecords/python/io/tf_record_test.py
tfrecords/python/util/__init__.py
tfrecords/python/util/compat.py
tfrecords/python/util/tf_decorator.py
tfrecords/python/util/tf_export.py
tfrecords/python/util/tf_inspect.py
tfrecords/testing/__init__.py
tfrecords/testing/demo_arrow.py
tfrecords/testing/demo_arrow_file.py
tfrecords/testing/demo_leveldb.py
tfrecords/testing/demo_lmdb.py
tfrecords/testing/demo_parquet.py
tfrecords/testing/demo_record.py
tfrecords-0.3.0.dist-info/METADATA
tfrecords-0.3.0.dist-info/WHEEL
tfrecords-0.3.0.dist-info/top_level.txt
tfrecords-0.3.0.dist-info/RECORD
